buildout_md5sums
