Metadata-Version: 1.0
Name: buildout-md5sums
Version: 0.1
Summary: A zc.builout extension that allows you to specify and enforce md5 checksums for all downloads
Home-page: http://www.python.org/pypi/buildout-md5sums
Author: Filip Noetzel
Author-email: filip+pypi@j03.de
License: Beerware
Platform: UNKNOWN
